icat/__init__.py
icat/anchorlist.py
icat/anchors.py
icat/data.py
icat/histogram.py
icat/histograms.py
icat/item.py
icat/model.py
icat/table.py
icat/utils.py
icat/view.py
icat/vue/anchors-table.vue
icat/vue/manager-table.vue
icat_iml-0.8.1.dist-info/licenses/LICENSE
icat_iml-0.8.1.dist-info/METADATA
icat_iml-0.8.1.dist-info/WHEEL
icat_iml-0.8.1.dist-info/top_level.txt
icat_iml-0.8.1.dist-info/RECORD
