Metadata-Version: 2.4
Name: icat-iml
Version: 0.8.1
Summary: Interactive Corpus Analysis Tool
Home-page: https://github.com/ORNL/icat
Author: Nathan Martindale, Scott L. Stewart
Author-email: icat-help@ornl.gov
Project-URL: Documentation, https://ornl.github.io/icat/
Classifier: Programming Language :: Python :: 3
Classifier: License :: OSI Approved :: BSD License
Classifier: Operating System :: OS Independent
Requires-Python: >=3.10
License-File: LICENSE
Requires-Dist: panel
Requires-Dist: pyviz_comms
Requires-Dist: numpy
Requires-Dist: pandas
Requires-Dist: scikit-learn
Requires-Dist: ipyanchorviz
Requires-Dist: altair
Requires-Dist: jupyter_bokeh
Requires-Dist: ipywidgets-bokeh
Requires-Dist: ipyvuetify
Requires-Dist: ipyvue
Requires-Dist: ipywidgets
Requires-Dist: jupyterlab-widgets
Requires-Dist: psutil
Dynamic: author
Dynamic: author-email
Dynamic: classifier
Dynamic: description
Dynamic: description-content-type
Dynamic: home-page
Dynamic: license-file
Dynamic: project-url
Dynamic: requires-dist
Dynamic: requires-python
Dynamic: summary
